ufaas/__init__.py
ufaas/_schemas.py
ufaas/client.py
ufaas/enums.py
ufaas/exceptions.py
ufaas/hold.py
ufaas/proposal.py
ufaas/py.typed
ufaas/services.py
ufaas/wallet.py
ufaas/fastapi/__init__.py
ufaas/fastapi/integration.py
ufaas-0.3.16.dist-info/licenses/LICENSE.txt
ufaas-0.3.16.dist-info/METADATA
ufaas-0.3.16.dist-info/WHEEL
ufaas-0.3.16.dist-info/top_level.txt
ufaas-0.3.16.dist-info/RECORD
